aitoolkit_base/__init__.py
aitoolkit_base/base_detector.py
aitoolkit_base/cli.py
aitoolkit_base/depth_estimator.py
aitoolkit_base/face_detector.py
aitoolkit_base/face_landmarker.py
aitoolkit_base/gesture_recognizer.py
aitoolkit_base/hand_landmarker.py
aitoolkit_base/image_classifier.py
aitoolkit_base/image_segmenter.py
aitoolkit_base/interactive_segmenter.py
aitoolkit_base/license_plate_detector.py
aitoolkit_base/model_trainer.py
aitoolkit_base/object_detector.py
aitoolkit_base/ocr_detector.py
aitoolkit_base/pose_landmarker.py
aitoolkit_base/style_transfer.py
aitoolkit_base/utils.py
aitoolkit_base/models/blaze_face_short_range.tflite
aitoolkit_base/models/deeplab_v3.tflite
aitoolkit_base/models/efficientnet_lite0.tflite
aitoolkit_base/models/face_detector.tflite
aitoolkit_base/models/face_landmarker.task
aitoolkit_base/models/gesture_recognizer.task
aitoolkit_base/models/hand_landmarker.task
aitoolkit_base/models/image_classifier.tflite
aitoolkit_base/models/object_detector.tflite
aitoolkit_base/models/pose_landmarker.task
aitoolkit_base/models/selfie_segmenter.tflite
aitoolkit_base-3.1.1.dist-info/licenses/LICENSE
aitoolkit_base-3.1.1.dist-info/METADATA
aitoolkit_base-3.1.1.dist-info/WHEEL
aitoolkit_base-3.1.1.dist-info/entry_points.txt
aitoolkit_base-3.1.1.dist-info/top_level.txt
aitoolkit_base-3.1.1.dist-info/RECORD
