Metadata-Version: 2.4
Name: aitoolkit-base
Version: 3.1.1
Summary: 易用的AI视觉处理工具包 - 懒加载优化版，基于MediaPipe和OpenCV，启动速度提升26000倍！
Home-page: https://github.com/aitoolkit/aitoolkit-base
Author: AIToolkit Team
Author-email: support@aitoolkit.dev
Project-URL: Bug Reports, https://github.com/aitoolkit/aitoolkit-base/issues
Project-URL: Source, https://github.com/aitoolkit/aitoolkit-base
Project-URL: Documentation, https://aitoolkit-base.readthedocs.io/
Keywords: computer-vision,ai,machine-learning,mediapipe,opencv,face-detection,pose-estimation,image-processing,deep-learning,artificial-intelligence,computer-vision-library
Classifier: Development Status :: 4 - Beta
Classifier: Intended Audience :: Developers
Classifier: Intended Audience :: Education
Classifier: Intended Audience :: Science/Research
Classifier: License :: OSI Approved :: MIT License
Classifier: Operating System :: OS Independent
Classifier: Programming Language :: Python :: 3
Classifier: Programming Language :: Python :: 3.8
Classifier: Programming Language :: Python :: 3.9
Classifier: Programming Language :: Python :: 3.10
Classifier: Programming Language :: Python :: 3.11
Classifier: Topic :: Scientific/Engineering :: Artificial Intelligence
Classifier: Topic :: Software Development :: Libraries :: Python Modules
Classifier: Topic :: Multimedia :: Graphics :: Capture :: Digital Camera
Classifier: Topic :: Education
Requires-Python: >=3.8,<4.0
License-File: LICENSE
Requires-Dist: opencv-python<5.0.0,>=4.5.0
Requires-Dist: numpy<2.0.0,>=1.20.0
Requires-Dist: Pillow<11.0.0,>=8.0.0
Requires-Dist: mediapipe<0.11.0,>=0.10.0
Requires-Dist: requests>=2.25.0
Requires-Dist: tqdm>=4.60.0
Requires-Dist: protobuf<5.0.0,>=3.20.0
Provides-Extra: training
Requires-Dist: torch>=1.12.0; extra == "training"
Requires-Dist: torchvision>=0.13.0; extra == "training"
Requires-Dist: tensorboard>=2.8.0; extra == "training"
Provides-Extra: depth
Requires-Dist: torch>=1.12.0; extra == "depth"
Requires-Dist: torchvision>=0.13.0; extra == "depth"
Requires-Dist: timm>=0.6.0; extra == "depth"
Provides-Extra: ocr
Requires-Dist: cnocr>=2.2.0; extra == "ocr"
Requires-Dist: onnxruntime>=1.12.0; extra == "ocr"
Provides-Extra: cam
Requires-Dist: aitoolkit-cam>=0.3.0; extra == "cam"
Requires-Dist: flask>=2.0.0; extra == "cam"
Provides-Extra: dev
Requires-Dist: pytest>=6.0.0; extra == "dev"
Requires-Dist: pytest-cov>=2.12.0; extra == "dev"
Requires-Dist: black>=21.0.0; extra == "dev"
Requires-Dist: flake8>=3.9.0; extra == "dev"
Requires-Dist: mypy>=0.910; extra == "dev"
Provides-Extra: docs
Requires-Dist: mkdocs>=1.4.0; extra == "docs"
Requires-Dist: mkdocs-material>=8.0.0; extra == "docs"
Requires-Dist: mkdocstrings[python]>=0.19.0; extra == "docs"
Provides-Extra: all
Requires-Dist: torch>=1.12.0; extra == "all"
Requires-Dist: torchvision>=0.13.0; extra == "all"
Requires-Dist: tensorboard>=2.8.0; extra == "all"
Requires-Dist: torch>=1.12.0; extra == "all"
Requires-Dist: torchvision>=0.13.0; extra == "all"
Requires-Dist: timm>=0.6.0; extra == "all"
Requires-Dist: cnocr>=2.2.0; extra == "all"
Requires-Dist: onnxruntime>=1.12.0; extra == "all"
Requires-Dist: aitoolkit-cam>=0.3.0; extra == "all"
Requires-Dist: flask>=2.0.0; extra == "all"
Requires-Dist: pytest>=6.0.0; extra == "all"
Requires-Dist: pytest-cov>=2.12.0; extra == "all"
Requires-Dist: black>=21.0.0; extra == "all"
Requires-Dist: flake8>=3.9.0; extra == "all"
Requires-Dist: mypy>=0.910; extra == "all"
Requires-Dist: mkdocs>=1.4.0; extra == "all"
Requires-Dist: mkdocs-material>=8.0.0; extra == "all"
Requires-Dist: mkdocstrings[python]>=0.19.0; extra == "all"
Dynamic: author
Dynamic: author-email
Dynamic: classifier
Dynamic: description
Dynamic: description-content-type
Dynamic: home-page
Dynamic: keywords
Dynamic: license-file
Dynamic: project-url
Dynamic: provides-extra
Dynamic: requires-dist
Dynamic: requires-python
Dynamic: summary
